nalej_platformer/__init__.py
nalej_platformer/exceptions.py
nalej_platformer/utils.py
nalej_platformer/cli/__init__.py
nalej_platformer/cli/config.py
nalej_platformer/cli/main.py
nalej_platformer/config/__init__.py
nalej_platformer/config/config.py
nalej_platformer/config/defaults.py
nalej_platformer/plan/__init__.py
nalej_platformer/plan/application.py
nalej_platformer/plan/azure.py
nalej_platformer/plan/hostnames.py
nalej_platformer/plan/ip_addresses.py
nalej_platformer/plan/k8s.py
nalej_platformer/plan/main.py
nalej_platformer/plan/management.py
nalej_platformer/plan/organization.py
nalej_platformer/plan/user.py
nalej_platformer/provider/__init__.py
nalej_platformer/provider/azure.py
nalej_platformer/provider/installer.py
nalej_platformer/provider/kubernetes.py
nalej_platformer/provider/provisioner.py
nalej_platformer/provider/public_api.py
nalej_platformer/provider/signup.py
nalej_platformer-0.5.5.dist-info/LICENSE
nalej_platformer-0.5.5.dist-info/METADATA
nalej_platformer-0.5.5.dist-info/WHEEL
nalej_platformer-0.5.5.dist-info/entry_points.txt
nalej_platformer-0.5.5.dist-info/top_level.txt
nalej_platformer-0.5.5.dist-info/RECORD
