Metadata-Version: 2.1
Name: nalej-platformer
Version: 0.5.5
Summary: Nalej Platform automation
Home-page: https://github.com/nalej/nalej-platformer
Author: Rodrigo Núñez
Author-email: rnunez@nalej.com
License: UNKNOWN
Platform: UNKNOWN
Classifier: Programming Language :: Python :: 3
Classifier: License :: OSI Approved :: Apache Software License
Classifier: Operating System :: OS Independent
Requires-Python: >=3.7
Requires-Dist: click (==7.0)
Requires-Dist: colorama (==0.4.3)
Requires-Dist: crayons (==0.3.0)
Requires-Dist: pyyaml (==5.3)
Requires-Dist: six (==1.14.0)
Requires-Dist: vistir (==0.5.0)
Requires-Dist: yaspin (==0.16.0)
